LICENSE
MANIFEST.in
README.rst
setup.py
apyio/__init__.py
apyio.egg-info/PKG-INFO
apyio.egg-info/SOURCES.txt
apyio.egg-info/dependency_links.txt
apyio.egg-info/entry_points.txt
apyio.egg-info/top_level.txt