Metadata-Version: 1.0
Name: apyio
Version: 0.2.0
Summary: Async wrappers for standard Python io streams.
Home-page: https://github.com/asyncdef/apyio
Author: Kevin Conway
Author-email: kevinjacobconway@gmail.com
License: Apache 2.0
Platform: UNKNOWN
